metaprompt/cli.py
metaprompt/templates/metaprompt.jinja
metaprompt/templates/metaprompt_assistant_partial.jinja
metaprompt-0.1.0.dist-info/METADATA
metaprompt-0.1.0.dist-info/WHEEL
metaprompt-0.1.0.dist-info/entry_points.txt
metaprompt-0.1.0.dist-info/RECORD
