Metadata-Version: 2.1
Name: metaprompt
Version: 0.1.0
Summary: 
Author: franz
Author-email: f@think-complete.com
Requires-Python: >=3.10,<4.0
Classifier: Programming Language :: Python :: 3
Classifier: Programming Language :: Python :: 3.10
Classifier: Programming Language :: Python :: 3.11
Requires-Dist: jinja2 (>=3.1.3,<4.0.0)
Requires-Dist: lxml (>=5.2.0,<6.0.0)
Requires-Dist: openai (>=1.14.3,<2.0.0)
